{"_ts":[1515514235,1515557495],"_r":{"breakdown":{"html":{"bytes":[11787,12083],"requests":[10,10]},"js":{"bytes":[289030,288709],"requests":[21,21]},"css":{"bytes":[25759,25756],"requests":[2,2]},"image":{"bytes":[409657,409748],"requests":[38,38]},"flash":{"bytes":[0,0],"requests":[0,0]},"font":{"bytes":[76092,75976],"requests":[3,3]},"video":{"bytes":[0,0],"requests":[0,0]},"other":{"bytes":[0,0],"requests":[0,0]}},"date":[1515514235,1515557495],"domElements":[309,309],"domInteractive":[1752,1384],"firstPaint":[1123,1044],"fullyLoaded":[7471,6545],"id":["180109_1A_67e9411596a68073ae34a9dd9b1b723c","180110_BC_c70149e7f5cee7c7650eb2039aade8e8"],"loadTime":[3565,1973],"render":[1179,1192],"SpeedIndex":[1596,1768],"TTFB":[354,292],"videoFrames":[[{"_i":"frame_0000.jpg","_t":0,"_vc":0},{"_i":"frame_0012.jpg","_t":1200,"_vc":17},{"_i":"frame_0014.jpg","_t":1400,"_vc":45},{"_i":"frame_0016.jpg","_t":1600,"_vc":76},{"_i":"frame_0021.jpg","_t":2100,"_vc":100},{"_i":"frame_0029.jpg","_t":2900,"_vc":100}],[{"_i":"frame_0000.jpg","_t":0,"_vc":0},{"_i":"frame_0012.jpg","_t":1200,"_vc":16},{"_i":"frame_0018.jpg","_t":1800,"_vc":68},{"_i":"frame_0020.jpg","_t":2000,"_vc":100}]],"visualComplete":[2100,2000],"lighthouse":[null,null],"pagespeed":[85,85]}}