{"_ts":[1515159789,1515203668],"_r":{"breakdown":{"html":{"bytes":[49816,49755],"requests":[7,7]},"js":{"bytes":[1126268,1049409],"requests":[21,19]},"css":{"bytes":[211651,211629],"requests":[4,4]},"image":{"bytes":[1190214,1190212],"requests":[17,17]},"flash":{"bytes":[0,0],"requests":[0,0]},"font":{"bytes":[158828,158775],"requests":[8,8]},"video":{"bytes":[0,0],"requests":[0,0]},"other":{"bytes":[3708,3708],"requests":[3,3]}},"date":[1515159789,1515203668],"domElements":[638,638],"domInteractive":[3721,3458],"firstPaint":[3737,3496],"fullyLoaded":[7430,7852],"id":["180105_GF_afb7cf98cba1e8b6d0a27a1f374c0a6c","180106_H2_462c78bbfaf1c78d52b1f89533f0cc74"],"loadTime":[6526,6544],"render":[3884,3685],"SpeedIndex":[4029,3806],"TTFB":[638,245],"videoFrames":[[{"_i":"frame_0000.jpg","_t":0,"_vc":0},{"_i":"frame_0039.jpg","_t":3900,"_vc":91},{"_i":"frame_0042.jpg","_t":4200,"_vc":94},{"_i":"frame_0058.jpg","_t":5800,"_vc":94},{"_i":"frame_0059.jpg","_t":5900,"_vc":100}],[{"_i":"frame_0000.jpg","_t":0,"_vc":0},{"_i":"frame_0037.jpg","_t":3700,"_vc":91},{"_i":"frame_0038.jpg","_t":3800,"_vc":94},{"_i":"frame_0054.jpg","_t":5400,"_vc":99},{"_i":"frame_0055.jpg","_t":5500,"_vc":100}]],"visualComplete":[5900,5500],"lighthouse":[null,null],"pagespeed":[52,52]}}